README.md
setup.cfg
setup.py
ipb_homework_checker/__init__.py
ipb_homework_checker/check_homework.py
ipb_homework_checker/checker.py
ipb_homework_checker/md_writer.py
ipb_homework_checker/print_repo_name.py
ipb_homework_checker/schema_manager.py
ipb_homework_checker/schema_tags.py
ipb_homework_checker/tasks.py
ipb_homework_checker/tools.py
ipb_homework_checker.egg-info/PKG-INFO
ipb_homework_checker.egg-info/SOURCES.txt
ipb_homework_checker.egg-info/dependency_links.txt
ipb_homework_checker.egg-info/entry_points.txt
ipb_homework_checker.egg-info/requires.txt
ipb_homework_checker.egg-info/top_level.txt