Metadata-Version: 1.2
Name: ipb-homework-checker
Version: 0.0.6
Summary: A generic homework checker.
Home-page: https://github.com/PRBonn/ipb_homework_checker
Author: Igor Bogoslavskyi
Author-email: igor.bogoslavskyi@uni-bonn.de
Maintainer: Igor Bogoslavskyi
Maintainer-email: igor.bogoslavskyi@uni-bonn.de
License: Apache 2.0
Download-URL: https://github.com/PRBonn/ipb_homework_checker/tarball/0.0.6
Keywords: ipb,homework-checker
Platform: UNKNOWN
Classifier: Environment :: Console
Classifier: Programming Language :: Python
Classifier: Intended Audience :: Developers
Classifier: License :: OSI Approved :: Apache Software License
